{
  "parent": "minecraft:recipes/root",
  "criteria": {
    "has_golden_savoyard": {
      "conditions": {
        "items": [
          {
            "items": [
              "knightsheraldry:golden_savoyard"
            ]
          }
        ]
      },
      "trigger": "minecraft:inventory_changed"
    },
    "has_the_recipe": {
      "conditions": {
        "recipe": "knightsheraldry:deco/unicorn_golden_savoyard"
      },
      "trigger": "minecraft:recipe_unlocked"
    },
    "has_unicorn": {
      "conditions": {
        "items": [
          {
            "items": [
              "knightsheraldry:unicorn"
            ]
          }
        ]
      },
      "trigger": "minecraft:inventory_changed"
    }
  },
  "requirements": [
    [
      "has_golden_savoyard",
      "has_unicorn",
      "has_the_recipe"
    ]
  ],
  "rewards": {
    "recipes": [
      "knightsheraldry:deco/unicorn_golden_savoyard"
    ]
  },
  "sends_telemetry_event": false
}