{
  "ranged": {
    "ammoRequirement": {
      "item1": {
        "amount": 2,
        "items": [
          "stoneycore:black_powder"
        ]
      },
      "item2": {
        "amount": 1,
        "items": [
          "minecraft:iron_nugget",
          "minecraft:gravel"
        ]
      },
      "item3": {
        "amount": 1,
        "items": [
          "minecraft:paper",
          "minecraft:short_grass"
        ]
      }
    },
    "baseDamage": 26.0,
    "damageType": "BLUDGEONING",
    "divergence": 2.5,
    "id": "musket",
    "maxUseTime": 1,
    "needsFlintAndSteel": true,
    "rechargeTime": 300,
    "soundEvent": "knightsheraldry:arquebus_close",
    "speed": 4.3,
    "useAnim": "BOW"
  },
  "usage": [
    "RANGED"
  ]
}