{
  "parent": "minecraft:recipes/root",
  "criteria": {
    "has_poleaxe": {
      "conditions": {
        "items": [
          {
            "items": "knightsheraldry:poleaxe"
          }
        ]
      },
      "trigger": "minecraft:inventory_changed"
    },
    "has_the_recipe": {
      "conditions": {
        "recipe": "knightsheraldry:manuscript/poleaxe"
      },
      "trigger": "minecraft:recipe_unlocked"
    }
  },
  "requirements": [
    [
      "has_the_recipe",
      "has_poleaxe"
    ]
  ],
  "rewards": {
    "recipes": [
      "knightsheraldry:manuscript/poleaxe"
    ]
  }
}